etg/__init__.py
etg/etg.py
etg-1.0.0.dist-info/licenses/LICENSE
etg-1.0.0.dist-info/METADATA
etg-1.0.0.dist-info/WHEEL
etg-1.0.0.dist-info/top_level.txt
etg-1.0.0.dist-info/RECORD
