Metadata-Version: 2.4
Name: etg
Version: 1.0.0
Summary: Библиотека для создания Telegram-ботов через собственный язык
Author-email: sosayto <thedefov@gmail.com>
Requires-Python: >=3.8
License-File: LICENSE
Requires-Dist: aiogram>=3.0.0
Dynamic: license-file
